raccgen/__init__.py
raccgen/generate.py
raccgen-1.0.0.dist-info/LICENSE
raccgen-1.0.0.dist-info/METADATA
raccgen-1.0.0.dist-info/WHEEL
raccgen-1.0.0.dist-info/top_level.txt
raccgen-1.0.0.dist-info/RECORD
